{
  "pages": {
    "https://www.mandalaourense.com/": {
      "title": "Mandala Ourense - Página web de mandala-ourense",
      "extracted_info": {
        "services": [
          "yoga\ndaoyin",
          "yoga\nnidra",
          "yoga y",
          "terapias\ncontacto",
          "terapias\ncontacto",
          "meditación",
          "formación"
        ],
        "languages": [],
        "schedules": [
          "horarios y precios",
          "horarios."
        ],
        "contact_info": [
          "info@mandalaourense.com"
        ],
        "key_terms": [
          "mandala",
          "yoga",
          "ourense",
          "actividades",
          "inicio",
          "terapias",
          "contacto",
          "horarios",
          "nuestras",
          "centro",
          "mandalas",
          "política",
          "página",
          "hatha",
          "daoyin",
          "nidra",
          "meditación",
          "precios",
          "condiciones",
          "bienvenida"
        ],
        "locations": [
          "Ourense",
          "Ourense"
        ]
      },
      "text_length": 1575,
      "summary": "This appears to be a contact page. Services mentioned: yoga y, terapias\ncontacto, yoga\nnidra, formación, meditación. Contains contact information. Includes scheduling information. Locations mentioned: Ourense."
    },
    "https://www.mandalaourense.com/actividades/": {
      "title": "Actividades - Página web de mandala-ourense",
      "extracted_info": {
        "services": [
          "yoga\ndaoyin",
          "yoga\nnidra",
          "yoga y",
          "yoga\ndaoyin",
          "yoga\nnidra",
          "yoga y",
          "terapias\ncontacto",
          "terapias\ncontacto",
          "meditación",
          "meditación",
          "formación"
        ],
        "languages": [],
        "schedules": [
          "horarios y precios",
          "horarios y precios",
          "horarios y precios"
        ],
        "contact_info": [
          "info@mandalaourense.com"
        ],
        "key_terms": [
          "yoga",
          "actividades",
          "horarios",
          "precios",
          "mandala",
          "ourense",
          "inicio",
          "terapias",
          "contacto",
          "hatha",
          "daoyin",
          "nidra",
          "meditación",
          "nuestras",
          "condiciones",
          "pincha",
          "política",
          "página"
        ],
        "locations": [
          "Ourense"
        ]
      },
      "text_length": 566,
      "summary": "This appears to be a homepage or landing page. Services mentioned: yoga y, terapias\ncontacto, yoga\nnidra, formación, meditación. Contains contact information. Includes scheduling information. Locations mentioned: Ourense."
    },
    "https://www.mandalaourense.com/actividades/hatha-yoga/": {
      "title": "Hatha Yoga - Página web de mandala-ourense",
      "extracted_info": {
        "services": [
          "yoga\ndaoyin",
          "yoga\nnidra",
          "yoga y",
          "yoga\ndaoyin",
          "yoga\nnidra",
          "yoga y",
          "yoga\ncuando",
          "yoga en",
          "yoga físico",
          "yoga fortalece",
          "yoga tiene",
          "yoga es",
          "yoga de",
          "yoga es",
          "yoga es",
          "terapias\ncontacto",
          "terapias\ncontacto",
          "meditación",
          "meditación"
        ],
        "languages": [],
        "schedules": [
          "horarios y precios",
          "horarios y precios"
        ],
        "contact_info": [
          "627305963",
          "679144037",
          "627305963",
          "679144037",
          "info@mandalaourense.com"
        ],
        "key_terms": [
          "yoga",
          "hatha",
          "cuerpo",
          "también",
          "espiritual",
          "pero",
          "sentido",
          "tradición",
          "sistema",
          "vida",
          "mente",
          "mandala",
          "ourense",
          "inicio",
          "actividades",
          "terapias",
          "contacto"
        ],
        "locations": [
          "Ourense"
        ]
      },
      "text_length": 3420,
      "summary": "This appears to be a contact page. Services mentioned: yoga y, yoga es, terapias\ncontacto, yoga\nnidra, yoga físico. Contains contact information. Includes scheduling information. Locations mentioned: Ourense."
    },
    "https://www.mandalaourense.com/actividades/daoyin-yoga/": {
      "title": "Daoyin Yoga - Página web de mandala-ourense",
      "extracted_info": {
        "services": [
          "yoga\ndaoyin",
          "yoga\nnidra",
          "yoga y",
          "yoga\ndaoyin",
          "yoga\nnidra",
          "yoga y",
          "yoga\nel",
          "yoga de",
          "masaje terapéutico",
          "terapias\ncontacto",
          "terapias\ncontacto",
          "terapias que",
          "tratamiento y",
          "tratamiento y",
          "tratamiento del",
          "meditación",
          "meditación"
        ],
        "languages": [
          "Spanish"
        ],
        "schedules": [
          "horarios y precios",
          "horarios y precios"
        ],
        "contact_info": [
          "675091191",
          "675091191",
          "info@mandalaourense.com"
        ],
        "key_terms": [
          "yoga",
          "daoyin",
          "ejercicios",
          "sistema",
          "recuperación",
          "china",
          "terapias",
          "contacto",
          "nuestras",
          "medicina",
          "tradicional",
          "salud",
          "prevención",
          "tratamiento",
          "mandala",
          "ourense",
          "inicio",
          "actividades",
          "hatha"
        ],
        "locations": [
          "Ourense"
        ]
      },
      "text_length": 3062,
      "summary": "This appears to be a contact page. Services mentioned: yoga y, terapias\ncontacto, yoga\nnidra, tratamiento y, masaje terapéutico. Contains contact information. Includes scheduling information. Locations mentioned: Ourense."
    },
    "https://www.mandalaourense.com/actividades/nidra-yoga-y-meditaci%C3%B3n/": {
      "title": "Nidra Yoga y Meditación - Página web de mandala-ourense",
      "extracted_info": {
        "services": [
          "yoga y",
          "yoga\ndaoyin",
          "yoga\nnidra",
          "yoga y",
          "yoga\ndaoyin",
          "yoga\nnidra",
          "yoga y",
          "yoga\nmetodología",
          "yoga nidra",
          "yoga nidra",
          "yoga nidra",
          "yoga moderno",
          "yoga nidra",
          "yoga nidra",
          "yoga nidra",
          "yoga del",
          "yoga nidra",
          "yoga nidra",
          "yoga nidra",
          "yoga nidra",
          "yoga nidra",
          "yoga\n    nidra",
          "yoga nidra",
          "yoga nidra",
          "yoga nidra",
          "yoga nidra",
          "yoga del",
          "yoga\n    nidra",
          "yoga nidra",
          "yoga nidra",
          "yoga nidra",
          "yoga alliance",
          "yoga y",
          "terapias\ncontacto",
          "terapias\ncontacto",
          "tratamientos de",
          "meditación",
          "meditación",
          "meditación",
          "meditación",
          "meditación",
          "meditación",
          "meditación",
          "meditación",
          "meditación",
          "meditación",
          "mindfulness",
          "mindfulness",
          "ayurveda"
        ],
        "languages": [],
        "schedules": [
          "horarios y precios",
          "horarios y precios"
        ],
        "contact_info": [
          "675091191",
          "675091191",
          "info@mandalaourense.com"
        ],
        "key_terms": [
          "yoga",
          "nidra",
          "meditación",
          "mente",
          "relajación",
          "fácil",
          "sueño",
          "consciente",
          "puede",
          "mandala",
          "contacto",
          "mental",
          "estado",
          "nuestro",
          "cuerpo",
          "práctica",
          "pero",
          "tiene",
          "subconsciente"
        ],
        "locations": [
          "Ourense"
        ]
      },
      "text_length": 4725,
      "summary": "This appears to be a contact page. Services mentioned: yoga\nmetodología, yoga y, yoga alliance, yoga\nnidra, terapias\ncontacto. Contains contact information. Includes scheduling information. Locations mentioned: Ourense."
    },
    "https://www.mandalaourense.com/actividades/horarios-y-precios/": {
      "title": "Horarios y Precios - Página web de mandala-ourense",
      "extracted_info": {
        "services": [
          "yoga\ndaoyin",
          "yoga\nnidra",
          "yoga y",
          "yoga\ndaoyin",
          "yoga\nnidra",
          "yoga y",
          "yoga\ncuota",
          "yoga\ncuota",
          "yoga\ncuota",
          "yoga nidra",
          "terapias\ncontacto",
          "terapias\ncontacto",
          "meditación",
          "meditación",
          "meditación"
        ],
        "languages": [],
        "schedules": [
          "horarios y precios - página web de mandala-ourense",
          "horarios y precios",
          "horarios y precios",
          "horarios para la temporada 2024 - 2025"
        ],
        "contact_info": [
          "info@mandalaourense.com"
        ],
        "key_terms": [
          "yoga",
          "actividades",
          "horarios",
          "precios",
          "nidra",
          "cuota",
          "clase",
          "hatha",
          "daoyin",
          "meditación",
          "nuestras",
          "semanales",
          "mensual",
          "semanal",
          "mandala",
          "ourense",
          "inicio",
          "terapias",
          "contacto"
        ],
        "locations": [
          "Ourense"
        ]
      },
      "text_length": 1169,
      "summary": "This appears to be a contact page. Services mentioned: yoga y, terapias\ncontacto, yoga\nnidra, yoga\ncuota, yoga nidra. Contains contact information. Includes scheduling information. Locations mentioned: Ourense."
    },
    "https://www.mandalaourense.com/actividades/nuestras-condiciones/": {
      "title": "Nuestras condiciones - Página web de mandala-ourense",
      "extracted_info": {
        "services": [
          "yoga\ndaoyin",
          "yoga\nnidra",
          "yoga y",
          "yoga\ndaoyin",
          "yoga\nnidra",
          "yoga y",
          "yoga hatha",
          "clases de yoga",
          "terapias\ncontacto",
          "terapias\ncontacto",
          "meditación",
          "meditación"
        ],
        "languages": [],
        "schedules": [
          "horarios y precios",
          "horarios y precios",
          "horario en el que estás interesado no ofrecemos clase, es"
        ],
        "contact_info": [
          "info@mandalaourense.com"
        ],
        "key_terms": [
          "yoga",
          "clases",
          "sala",
          "antes",
          "nuestras",
          "condiciones",
          "mandala",
          "plaza",
          "clase",
          "práctica",
          "actividades",
          "hatha",
          "necesario",
          "pago",
          "asistencia",
          "días",
          "motivo",
          "personales",
          "todos"
        ],
        "locations": [
          "Ourense"
        ]
      },
      "text_length": 3264,
      "summary": "This appears to be a contact page. Services mentioned: yoga y, terapias\ncontacto, yoga\nnidra, yoga hatha, clases de yoga. Contains contact information. Includes scheduling information. Locations mentioned: Ourense."
    },
    "https://www.mandalaourense.com/terapias/": {
      "title": "Terapias - Página web de mandala-ourense",
      "extracted_info": {
        "services": [
          "yoga\ndaoyin",
          "yoga\nnidra",
          "yoga y",
          "masaje y",
          "masajes y",
          "terapias\ncontacto",
          "terapias\ncontacto",
          "meditación",
          "formación"
        ],
        "languages": [],
        "schedules": [
          "horarios y precios"
        ],
        "contact_info": [
          "info@mandalaourense.com"
        ],
        "key_terms": [
          "terapias",
          "mandala",
          "yoga",
          "ourense",
          "inicio",
          "actividades",
          "contacto",
          "política",
          "página",
          "hatha",
          "daoyin",
          "nidra",
          "meditación",
          "horarios",
          "precios",
          "nuestras",
          "condiciones",
          "servicios",
          "terapéuticos",
          "interesados"
        ],
        "locations": [
          "Ourense"
        ]
      },
      "text_length": 709,
      "summary": "This appears to be a homepage or landing page. Services mentioned: yoga y, terapias\ncontacto, yoga\nnidra, masaje y, masajes y. Contains contact information. Includes scheduling information. Locations mentioned: Ourense."
    },
    "https://www.mandalaourense.com/cursos-eventos/constelaciones-familiares/": {
      "title": "Constelaciones Familiares - Página web de mandala-ourense",
      "extracted_info": {
        "services": [
          "yoga\ndaoyin",
          "yoga\nnidra",
          "yoga y",
          "terapias\ncontacto",
          "terapias\ncontacto",
          "terapia de",
          "meditación"
        ],
        "languages": [],
        "schedules": [
          "horarios y precios"
        ],
        "contact_info": [
          "609834193",
          "609834193",
          "info@mandalaourense.com"
        ],
        "key_terms": [
          "familiares",
          "constelaciones",
          "constelación",
          "relaciones",
          "cada",
          "persona",
          "personal",
          "grupo",
          "personas",
          "forma",
          "trabajo",
          "yoga",
          "realiza",
          "realizan",
          "terapia",
          "pueden"
        ],
        "locations": [
          "Ourense"
        ]
      },
      "text_length": 4478,
      "summary": "This appears to be a contact page. Services mentioned: yoga y, terapias\ncontacto, yoga\nnidra, terapia de, meditación. Contains contact information. Includes scheduling information. Locations mentioned: Ourense."
    },
    "https://www.mandalaourense.com/contacto/": {
      "title": "Contacto - Página web de mandala-ourense",
      "extracted_info": {
        "services": [
          "yoga\ndaoyin",
          "yoga\nnidra",
          "yoga y",
          "yoga nidra",
          "terapias\ncontacto",
          "terapias\ncontacto",
          "meditación",
          "meditación",
          "formación",
          "formación",
          "formación"
        ],
        "languages": [],
        "schedules": [
          "horarios y precios"
        ],
        "contact_info": [
          "679144037",
          "627305963",
          "675091191",
          "675091191",
          "679144037",
          "627305963",
          "675091191",
          "675091191",
          "info@mandalaourense.com",
          "info@mandalaourense.com",
          "C/ Dr"
        ],
        "key_terms": [
          "yoga",
          "política",
          "contacto",
          "actividades",
          "cookies",
          "mandala",
          "ourense",
          "hatha",
          "mandalaourense",
          "información",
          "google",
          "maps",
          "inicio",
          "terapias",
          "daoyin",
          "nidra",
          "meditación",
          "nuestras",
          "ubicación"
        ],
        "locations": [
          "Ourense",
          "Ourense",
          "C/ Dr"
        ]
      },
      "text_length": 1552,
      "summary": "This appears to be a contact page. Services mentioned: yoga y, terapias\ncontacto, yoga\nnidra, yoga nidra, formación. Contains contact information. Includes scheduling information. Locations mentioned: Ourense, C/ Dr."
    },
    "https://www.mandalaourense.com/about/": {
      "title": "Aviso legal - Página web de mandala-ourense",
      "extracted_info": {
        "services": [
          "yoga\ndaoyin",
          "yoga\nnidra",
          "yoga y",
          "terapias\ncontacto",
          "terapias\ncontacto",
          "meditación",
          "formación",
          "formación",
          "formación",
          "formación",
          "formación",
          "formación",
          "formación"
        ],
        "languages": [],
        "schedules": [
          "horarios y precios"
        ],
        "contact_info": [
          "675091191",
          "627305963",
          "679144037",
          "644503174",
          "675091191",
          "627305963",
          "679144037",
          "644503174",
          "info@mandalaourense.com",
          "info@mandalaourense.com",
          "C/ Dr"
        ],
        "key_terms": [
          "página",
          "mandala",
          "contenidos",
          "actividades",
          "acceso",
          "usuario",
          "información",
          "datos",
          "enlaces",
          "condiciones",
          "sitio",
          "usuarios",
          "clientes",
          "cualquier",
          "aviso",
          "contacto",
          "titular",
          "denominación",
          "social",
          "servicios"
        ],
        "locations": [
          "Ourense",
          "Ourense",
          "C/ Dr"
        ]
      },
      "text_length": 5761,
      "summary": "This appears to be a contact page. Services mentioned: yoga y, terapias\ncontacto, yoga\nnidra, formación, meditación. Contains contact information. Includes scheduling information. Locations mentioned: Ourense, C/ Dr."
    }
  },
  "overall_summary": {
    "total_pages": 11,
    "services_offered": [
      "yoga alliance",
      "masaje terapéutico",
      "masajes y",
      "ayurveda",
      "tratamiento del",
      "terapias que",
      "formación",
      "yoga en",
      "meditación",
      "clases de yoga",
      "yoga es",
      "yoga y",
      "terapias\ncontacto",
      "masaje y",
      "yoga físico",
      "yoga de",
      "yoga hatha",
      "yoga\ncuando",
      "yoga del",
      "yoga\nmetodología",
      "tratamiento y",
      "yoga tiene",
      "yoga moderno",
      "yoga nidra",
      "yoga\n    nidra",
      "tratamientos de",
      "mindfulness",
      "yoga\nnidra",
      "terapia de",
      "yoga\ncuota",
      "yoga\nel",
      "yoga fortalece",
      "yoga\ndaoyin"
    ],
    "languages": [
      "Spanish"
    ],
    "contact_information": [
      "679144037",
      "info@mandalaourense.com",
      "C/ Dr",
      "609834193",
      "627305963",
      "644503174",
      "675091191"
    ],
    "site_purpose": "This website appears to be for a yoga studio called Mandala located in Ourense, Galicia. They offer services including yoga alliance, masaje terapéutico, masajes y, ayurveda, tratamiento del"
  },
  "all_services": [
    "yoga alliance",
    "masaje terapéutico",
    "masajes y",
    "ayurveda",
    "tratamiento del",
    "terapias que",
    "formación",
    "yoga en",
    "meditación",
    "clases de yoga",
    "yoga es",
    "yoga y",
    "terapias\ncontacto",
    "masaje y",
    "yoga físico",
    "yoga de",
    "yoga hatha",
    "yoga\ncuando",
    "yoga del",
    "yoga\nmetodología",
    "tratamiento y",
    "yoga tiene",
    "yoga moderno",
    "yoga nidra",
    "yoga\n    nidra",
    "tratamientos de",
    "mindfulness",
    "yoga\nnidra",
    "terapia de",
    "yoga\ncuota",
    "yoga\nel",
    "yoga fortalece",
    "yoga\ndaoyin"
  ],
  "all_languages": [
    "Spanish"
  ],
  "all_contact_info": [
    "679144037",
    "info@mandalaourense.com",
    "C/ Dr",
    "609834193",
    "627305963",
    "644503174",
    "675091191"
  ]
}